{
  "tags": [
    "Malware",
    "Fraud",
    "Exitscam",
    "Paster",
    "Althopping",
    "Inactive",
    "Owner",
    "Staff"
  ],
  "users": [
    {
      "nickname": "Astroghostf",
      "id": "1208128286471880807",
      "tags": [
        "Malware",
        "Paster",
        "Owner"
      ],
      "note": "Ex-Co-Owner of Ronix, nuked Pulsery.",
      "refs": [
        "https://v3rm.net/threads/cw-astroghost-aka-nuker-predator-scammer-ratter.21469/",
        "https://v3rm.net/threads/cw-about-astroghost-getting-paid-by-setinstance-then-nuked-nexora.22007/",
        "https://www.youtube.com/watch?v=zUShmzrj9p8"
      ],
      "username": "@astroghxst",
      "created": "2024-02-16",
      "avatar": "https://cdn.discordapp.com/avatars/1208128286471880807/79faafe4a8f33b6fa07d6079adfdcffc"
    },
    {
      "nickname": "Kronos/Ronver/Darklight/Nexity",
      "id": "335041885485662209",
      "tags": [
        "Alt-Hopping",
        "Owner"
      ],
      "note": "Owner of Ronix Executor. Goes under many different Aliases. Has been in several controversies.",
      "refs": [
        "https://v3rm.net/threads/cw-ronver-nexity-ronix-danner-darklight.20989/",
        "https://v3rm.net/threads/cw-blah-blah-nexity-darknight-whatever.15084/",
        "https://v3rm.net/threads/cw-nexity-scammer-manipulator.12156/",
        "https://www.youtube.com/watch?v=zUShmzrj9p8"
      ],
      "username": "@projectkrono",
      "created": "2017-07-13",
      "avatar": "https://cdn.discordapp.com/avatars/335041885485662209/326e07efbae54e09123b0f6587565e57"
    },
    {
      "nickname": "ValeDreamer",
      "id": "Unknown",
      "tags": [
        "Malware",
        "Fraud",
        "Exitscam",
        "Paster",
        "Alt-Hopping"
      ],
      "note": "Uses many different aliases and accounts, basically Consist and Nevy.",
      "refs": [
        "https://v3rm.net/threads/community-warning-argon-nevy-valedreamer-kq.19759/",
        "https://v3rm.net/threads/valedreamer-oxycontin-eulen.8595/",
        "https://v3rm.net/threads/valedreamer-is-back-and-its-funnier-than-ever.12545/",
        "https://www.reddit.com/r/robloxhackers/comments/1doefsd/valedreamer_has_ratted_over_500_people_with_proof/"
      ],
      "username": "Unknown Account",
      "created": "2025-08-10",
      "avatar": "https://cdn.discordapp.com/embed/avatars/4.png"
    },
    {
      "nickname": "Consist",
      "id": "Unknown",
      "tags": [
        "Malware",
        "Fraud",
        "Exitscam",
        "Paster",
        "Alt-Hopping"
      ],
      "note": "Uses many different aliases and accounts, basically Nevy and ValeDreamer.",
      "refs": [
        "https://v3rm.net/threads/community-warning-argon-nevy-valedreamer-kq.19759/",
        "https://v3rm.net/threads/valedreamer-oxycontin-eulen.8595/"
      ],
      "username": "Unknown Account",
      "created": "2025-08-10",
      "avatar": "https://cdn.discordapp.com/embed/avatars/0.png"
    },
    {
      "nickname": "Nevy",
      "id": "Unknown",
      "tags": [
        "Malware",
        "Fraud",
        "Exitscam",
        "Paster",
        "Alt-Hopping"
      ],
      "note": "Uses many different aliases and accounts, basically ValeDreamer and Consist.",
      "refs": [
        "https://v3rm.net/threads/community-warning-argon-nevy-valedreamer-kq.19759/",
        "https://v3rm.net/threads/valedreamer-oxycontin-eulen.8595/"
      ],
      "username": "Unknown Account",
      "created": "2025-08-10",
      "avatar": "https://cdn.discordapp.com/embed/avatars/0.png"
    },
    {
      "nickname": "Clarity",
      "id": "1372966978964426883",
      "tags": [
        "Malware",
        "Fraud",
        "Exitscam",
        "Paster",
        "Alt-Hopping",
        "Owner"
      ],
      "note": "Ex-Co-Owner of Luna, Ex-Co-Founder of Paradox, collaborates with other people in this blacklist. Tried to rat Luna and Atlantis.",
      "refs": [
        "https://v3rm.net/threads/2-in-1-cw-element-5ive-softworks-orange-luna-paradox-clarity.15041/",
        "https://v3rm.net/threads/yeah-dont-buy-paradox-hosting-cw.15927/",
        "https://v3rm.net/threads/cw-vexyflows-crossflows-clarityflows-clawcore-atlantis-rat.17883/"
      ],
      "username": "@destinyxxxowo",
      "created": "2025-05-16",
      "avatar": "https://cdn.discordapp.com/avatars/1372966978964426883/565bf3b9b960796a97482d4ac6917b2f"
    },
    {
      "nickname": "Etheriut",
      "id": "Unknown",
      "tags": [
        "Fraud",
        "Owner"
      ],
      "note": "Owner of AWP, left the executor detected and broken.",
      "refs": [
        "https://v3rm.net/threads/why-use-awp.21080/"
      ],
      "username": "Unknown Account",
      "created": "2025-08-10",
      "avatar": "https://cdn.discordapp.com/embed/avatars/4.png"
    },
    {
      "nickname": "Merkuri",
      "id": "Unknown",
      "tags": [
        "Paster",
        "Alt-Hopping",
        "Staff"
      ],
      "note": "Ex-Staff Member at AWP. Exposed for using AI to answer questions about C++ and Hyperion.",
      "refs": [
        "https://v3rm.net/threads/awp-where-is-merkuri.22061/"
      ],
      "username": "Unknown Account",
      "created": "2025-08-10",
      "avatar": "https://cdn.discordapp.com/embed/avatars/2.png"
    },
    {
      "nickname": "Glosary",
      "id": "1224779977317285932",
      "tags": [
        "Paster",
        "Owner"
      ],
      "note": "Owner of Arctic Executor, a pasted executor. Many figures on this blacklist also being in that server while also being the result of Argon/Atlantis.",
      "username": "@glosaryyy",
      "created": "2024-04-02",
      "avatar": "https://cdn.discordapp.com/avatars/1224779977317285932/12a6e9079c35dce4bbf2702494a09e64"
    },
    {
      "nickname": "Hexxr",
      "id": "709238641372823564",
      "tags": [
        "Exitscam",
        "Malware",
        "Alt-Hopping"
      ],
      "note": "Pedophile, drug addict, ratter.",
      "refs": [
        "https://v3rm.net/threads/hexxr-a-serious-warning-to-the-community.22515/",
        "https://v3rm.net/threads/cw-hexxr-hexpatch-ketxne.22285/"
      ],
      "username": "@vd75",
      "created": "2020-05-11",
      "avatar": "https://cdn.discordapp.com/avatars/709238641372823564/d09b7b2d2cdae12f4ef58e4fc34f2cf8"
    },
    {
      "nickname": "Kjs14/bxp0",
      "id": "709238641372823564",
      "tags": [
        "Paster",
        "Alt-Hopping",
        "Owner"
      ],
      "note": "General skid.",
      "refs": [
        "https://v3rm.net/threads/cw-_bxp0-kjs_14-skiddyskiddyskid.22276/"
      ],
      "username": "@vd75",
      "created": "2020-05-11",
      "avatar": "https://cdn.discordapp.com/avatars/709238641372823564/d09b7b2d2cdae12f4ef58e4fc34f2cf8"
    },
    {
      "nickname": "Darkness",
      "id": "1133943599344656394",
      "tags": [
        "Paster",
        "Owner"
      ],
      "note": "Owner of Vornex, a new Android exploit, suspected to be an alternate account.",
      "username": "@nightnessinthedark",
      "created": "2023-07-27",
      "avatar": "https://cdn.discordapp.com/avatars/1133943599344656394/86ee8110ffed7430650274462d9149a0"
    },
    {
      "nickname": "Blurzz",
      "id": "1231277593332809820",
      "tags": [
        "Paster",
        "Owner"
      ],
      "note": "Owner of Fluxteam, now renamed Subz.",
      "username": "@blurzz.sys",
      "created": "2024-04-20",
      "avatar": "https://cdn.discordapp.com/avatars/1231277593332809820/3f978a9775f4df874ceb69d7789598e1"
    },
    {
      "nickname": "Frame/ycqm",
      "id": "Unknown",
      "tags": [
        "Paster",
        "Malware",
        "Exitscam",
        "Alt-Hopping",
        "Owner"
      ],
      "note": "Previous owner of Canda, Connection to Macsploit. Tends to spread malware through projects he is involved in.",
      "refs": [
        "https://v3rm.net/threads/cw-warning-about-frame-aka-ycqm-%E2%80%93-scammer-racist-and-distributor-of-malware.22707/#post-179135"
      ],
      "username": "Unknown Account",
      "created": "2025-08-10",
      "avatar": "https://cdn.discordapp.com/embed/avatars/2.png"
    },
    {
      "nickname": "Orange/Mythic",
      "id": "Unknown",
      "tags": [
        "Asshole",
        "Owner",
        "Inactive"
      ],
      "note": "Owner of Element before he deleted it. Just a general asshole.",
      "refs": [
        "https://v3rm.net/threads/cw-orange-element-the-safety-of-the-roblox-exploiting-com.14531/",
        "https://v3rm.net/threads/2-in-1-cw-element-5ive-softworks-orange-luna-paradox-clarity.15041/",
        "https://v3rm.net/threads/cw-element-orange-part-2-daily-episodes-of-element-drama.15611/"
      ],
      "username": "Unknown Account",
      "created": "2025-08-10",
      "avatar": "https://cdn.discordapp.com/embed/avatars/5.png"
    },
    {
      "nickname": "kq",
      "id": "1241238935288545322",
      "tags": [
        "Paster",
        "Fraud"
      ],
      "note": "Owner of Zorara, now known as Drift. Has scammed in the past. Zorara is based off Xeno, and they discretely hid that from their community.",
      "refs": [
        "https://v3rm.net/threads/community-warning-argon-nevy-valedreamer-kq.19759/"
      ],
      "username": "@kqrara",
      "created": "2024-05-18",
      "avatar": "https://cdn.discordapp.com/avatars/1241238935288545322/19cd591ca5561cc7b16dafbc2c140f85"
    },
    {
      "nickname": "crossflows",
      "id": "1118986940721668157",
      "tags": [
        "Malware",
        "Paster",
        "Fraud",
        "Alt-Hopping",
        "Exitscam",
        "Inactive"
      ],
      "note": "Was heavily involved in the whole Atlantis/Argon situation, hasn't been seen since.",
      "refs": [
        "https://v3rm.net/threads/cw-vexyflows-crossflows-clarityflows-clawcore-atlantis-rat.17883/"
      ],
      "username": "@crossflows",
      "created": "2023-06-15",
      "avatar": "https://cdn.discordapp.com/avatars/1118986940721668157/0549a898bac4a17048becf8bd89e3bdc"
    },
    {
      "nickname": "Lxzp/Yoru",
      "id": "1319549583017250908",
      "tags": [
        "Paster",
        "Fraud",
        "Malware",
        "Alt-Hopping",
        "Owner"
      ],
      "note": "Former owner of Atlantis. Exit-scammed in the past as Yoru before coming back as Lxzp Involved in the raiding and stealing of Luna's server, as well as distributing an infected injector.",
      "refs": [
        "https://cheat.today/#:~:text=3-,Atlantis,-Unknown",
        "https://v3rm.net/threads/be-aware-lxzp.17376/",
        "https://v3rm.net/threads/cw-lxzp-yoru-savage-dtbu-skidding-ratting-raiding.17437/"
      ],
      "username": "@_lxzp",
      "created": "2024-12-20",
      "avatar": "https://cdn.discordapp.com/avatars/1319549583017250908/a_70d369abf7bf1496f58ad610f56f5c7d"
    },
    {
      "nickname": "Sakpot",
      "id": "888177948111274047",
      "tags": [
        "Paster",
        "Exitscam",
        "Fraud",
        "Malware",
        "Owner"
      ],
      "note": "He's basically be involved in any malicious exploit or exitscam known to man while also monetising them all. He found the infinite money glitch.",
      "refs": [
        "https://urbandictionary.com/define.php?term=sakpot",
        "https://youtube.com/watch?v=TGifTyjE-rg"
      ],
      "username": "@sakpog",
      "created": "2021-09-16",
      "avatar": "https://cdn.discordapp.com/avatars/888177948111274047/ab6998fed55d5deb374c971a464e1686"
    }
  ]
}
